nvsmpy/__init__.py
nvsmpy/cuda_cluster.py
nvsmpy/cuda_gpu.py
nvsmpy/utils.py
nvsmpy-0.2.2.dist-info/LICENSE
nvsmpy-0.2.2.dist-info/METADATA
nvsmpy-0.2.2.dist-info/WHEEL
nvsmpy-0.2.2.dist-info/top_level.txt
nvsmpy-0.2.2.dist-info/RECORD
