Metadata-Version: 2.1
Name: nvsmpy
Version: 0.2.2
Summary: Find unoccupied GPUs on multi-user systems
Home-page: https://github.com/lorenz-h/nvsmpy
Author: lorenz-h
Author-email: lorenz.hetzel@yahoo.de
License: UNKNOWN
Platform: UNKNOWN
Classifier: Programming Language :: Python :: 3
Classifier: License :: OSI Approved :: BSD License
Classifier: Operating System :: OS Independent
Requires-Python: >:3.5
Requires-Dist: psutil
Requires-Dist: pynvml
